[{"variante":["https://w3id.org/toRoll/vocs/taginOM/he_1000"],"variant":["https://w3id.org/toRoll/vocs/taginOM/he_1000"],"varian":["https://w3id.org/toRoll/vocs/taginOM/he_1000"],"varia":["https://w3id.org/toRoll/vocs/taginOM/he_1000"],"vari":["https://w3id.org/toRoll/vocs/taginOM/he_1000"],"var":["https://w3id.org/toRoll/vocs/taginOM/he_1000"],"va":["https://w3id.org/toRoll/vocs/taginOM/he_1000"],"v":["https://w3id.org/toRoll/vocs/taginOM/he_1000"],"ariante":["https://w3id.org/toRoll/vocs/taginOM/he_1000"],"ariant":["https://w3id.org/toRoll/vocs/taginOM/he_1000"],"arian":["https://w3id.org/toRoll/vocs/taginOM/he_1000"],"aria":["https://w3id.org/toRoll/vocs/taginOM/he_1000"],"ari":["https://w3id.org/toRoll/vocs/taginOM/he_1000"],"ar":["https://w3id.org/toRoll/vocs/taginOM/he_1000"],"a":["https://w3id.org/toRoll/vocs/taginOM/he_1000"],"riante":["https://w3id.org/toRoll/vocs/taginOM/he_1000"],"riant":["https://w3id.org/toRoll/vocs/taginOM/he_1000"],"rian":["https://w3id.org/toRoll/vocs/taginOM/he_1000"],"ria":["https://w3id.org/toRoll/vocs/taginOM/he_1000"],"ri":["https://w3id.org/toRoll/vocs/taginOM/he_1000"],"r":["https://w3id.org/toRoll/vocs/taginOM/he_1000"],"iante":["https://w3id.org/toRoll/vocs/taginOM/he_1000"],"iant":["https://w3id.org/toRoll/vocs/taginOM/he_1000"],"ian":["https://w3id.org/toRoll/vocs/taginOM/he_1000"],"ia":["https://w3id.org/toRoll/vocs/taginOM/he_1000"],"i":["https://w3id.org/toRoll/vocs/taginOM/he_1000"],"ante":["https://w3id.org/toRoll/vocs/taginOM/he_1000"],"ant":["https://w3id.org/toRoll/vocs/taginOM/he_1000"],"an":["https://w3id.org/toRoll/vocs/taginOM/he_1000"],"nte":["https://w3id.org/toRoll/vocs/taginOM/he_1000"],"nt":["https://w3id.org/toRoll/vocs/taginOM/he_1000"],"n":["https://w3id.org/toRoll/vocs/taginOM/he_1000"],"te":["https://w3id.org/toRoll/vocs/taginOM/he_1000"],"t":["https://w3id.org/toRoll/vocs/taginOM/he_1000"],"e":["https://w3id.org/toRoll/vocs/taginOM/he_1000"]},{"des":["https://w3id.org/toRoll/vocs/taginOM/he_1000"],"de":["https://w3id.org/toRoll/vocs/taginOM/he_1000"],"d":["https://w3id.org/toRoll/vocs/taginOM/he_1000"]},{"es":["https://w3id.org/toRoll/vocs/taginOM/he_1000"],"s":["https://w3id.org/toRoll/vocs/taginOM/he_1000"],"h":["https://w3id.org/toRoll/vocs/taginOM/he_1000"],"he":["https://w3id.org/toRoll/vocs/taginOM/he_1000"],"mit":["https://w3id.org/toRoll/vocs/taginOM/he_1000"],"mi":["https://w3id.org/toRoll/vocs/taginOM/he_1000"],"m":["https://w3id.org/toRoll/vocs/taginOM/he_1000"]},{"it":["https://w3id.org/toRoll/vocs/taginOM/he_1000"],"einem":["https://w3id.org/toRoll/vocs/taginOM/he_1000"],"eine":["https://w3id.org/toRoll/vocs/taginOM/he_1000"],"ein":["https://w3id.org/toRoll/vocs/taginOM/he_1000"],"ei":["https://w3id.org/toRoll/vocs/taginOM/he_1000"],"inem":["https://w3id.org/toRoll/vocs/taginOM/he_1000"],"ine":["https://w3id.org/toRoll/vocs/taginOM/he_1000"],"in":["https://w3id.org/toRoll/vocs/taginOM/he_1000"],"tag":["https://w3id.org/toRoll/vocs/taginOM/he_1000"],"ta":["https://w3id.org/toRoll/vocs/taginOM/he_1000"]},{"nem":["https://w3id.org/toRoll/vocs/taginOM/he_1000"],"ne":["https://w3id.org/toRoll/vocs/taginOM/he_1000"],"em":["https://w3id.org/toRoll/vocs/taginOM/he_1000"],"ag":["https://w3id.org/toRoll/vocs/taginOM/he_1000"],"auf":["https://w3id.org/toRoll/vocs/taginOM/he_1000"],"au":["https://w3id.org/toRoll/vocs/taginOM/he_1000"],"ersten":["https://w3id.org/toRoll/vocs/taginOM/he_1000"],"erste":["https://w3id.org/toRoll/vocs/taginOM/he_1000"],"erst":["https://w3id.org/toRoll/vocs/taginOM/he_1000"],"ers":["https://w3id.org/toRoll/vocs/taginOM/he_1000"],"position":["https://w3id.org/toRoll/vocs/taginOM/he_1000"],"positio":["https://w3id.org/toRoll/vocs/taginOM/he_1000"],"positi":["https://w3id.org/toRoll/vocs/taginOM/he_1000"],"posit":["https://w3id.org/toRoll/vocs/taginOM/he_1000"],"posi":["https://w3id.org/toRoll/vocs/taginOM/he_1000"],"pos":["https://w3id.org/toRoll/vocs/taginOM/he_1000"],"po":["https://w3id.org/toRoll/vocs/taginOM/he_1000"],"p":["https://w3id.org/toRoll/vocs/taginOM/he_1000"]},{"g":["https://w3id.org/toRoll/vocs/taginOM/he_1000"],"uf":["https://w3id.org/toRoll/vocs/taginOM/he_1000"],"u":["https://w3id.org/toRoll/vocs/taginOM/he_1000"],"f":["https://w3id.org/toRoll/vocs/taginOM/he_1000"],"der":["https://w3id.org/toRoll/vocs/taginOM/he_1000"],"er":["https://w3id.org/toRoll/vocs/taginOM/he_1000"],"rsten":["https://w3id.org/toRoll/vocs/taginOM/he_1000"],"rste":["https://w3id.org/toRoll/vocs/taginOM/he_1000"],"rst":["https://w3id.org/toRoll/vocs/taginOM/he_1000"],"rs":["https://w3id.org/toRoll/vocs/taginOM/he_1000"],"sten":["https://w3id.org/toRoll/vocs/taginOM/he_1000"],"ste":["https://w3id.org/toRoll/vocs/taginOM/he_1000"],"st":["https://w3id.org/toRoll/vocs/taginOM/he_1000"],"osition":["https://w3id.org/toRoll/vocs/taginOM/he_1000"],"ositio":["https://w3id.org/toRoll/vocs/taginOM/he_1000"],"ositi":["https://w3id.org/toRoll/vocs/taginOM/he_1000"],"osit":["https://w3id.org/toRoll/vocs/taginOM/he_1000"],"osi":["https://w3id.org/toRoll/vocs/taginOM/he_1000"],"os":["https://w3id.org/toRoll/vocs/taginOM/he_1000"],"o":["https://w3id.org/toRoll/vocs/taginOM/he_1000"],"sition":["https://w3id.org/toRoll/vocs/taginOM/he_1000"],"sitio":["https://w3id.org/toRoll/vocs/taginOM/he_1000"],"siti":["https://w3id.org/toRoll/vocs/taginOM/he_1000"],"sit":["https://w3id.org/toRoll/vocs/taginOM/he_1000"],"si":["https://w3id.org/toRoll/vocs/taginOM/he_1000"]},{"ten":["https://w3id.org/toRoll/vocs/taginOM/he_1000"],"en":["https://w3id.org/toRoll/vocs/taginOM/he_1000"],"ition":["https://w3id.org/toRoll/vocs/taginOM/he_1000"],"itio":["https://w3id.org/toRoll/vocs/taginOM/he_1000"],"iti":["https://w3id.org/toRoll/vocs/taginOM/he_1000"],"tion":["https://w3id.org/toRoll/vocs/taginOM/he_1000"],"tio":["https://w3id.org/toRoll/vocs/taginOM/he_1000"],"ti":["https://w3id.org/toRoll/vocs/taginOM/he_1000"],"ion":["https://w3id.org/toRoll/vocs/taginOM/he_1000"],"io":["https://w3id.org/toRoll/vocs/taginOM/he_1000"]},{"on":["https://w3id.org/toRoll/vocs/taginOM/he_1000"]},{}]